{
    "internal-dpl-clock": "",
    "o2sim-mctrack-proxy": {
        "ready-state-policy": "keep",
        "channel-config": "name=o2sim-mctrack-proxy,type=sub,method=connect,address=ipc:\/\/\/tmp\/o2sim-hitmerger-kineforward-28302,rateLogging=100",
        "orbit-offset-enumeration": "0",
        "orbit-multiplier-enumeration": "0",
        "start-value-enumeration": "0",
        "end-value-enumeration": "-1",
        "step-value-enumeration": "1"
    },
    "em-lmee-lf-cocktail": {
        "cfgCollisionSystem": "200",
        "cfgWriteTTree": "true",
        "cfgDoPairing": "false",
        "cfgMaxEta": "0.800000012",
        "cfgMinPt": "0.200000003",
        "cfgMaxPt": "10",
        "cfgNBinsMee": "1200",
        "cfgMinMee": "0",
        "cfgMaxMee": "6",
        "cfgNBinsPtee": "400",
        "cfgMinPtee": "0",
        "cfgMaxPtee": "10",
        "cfgResolType": "2",
        "cfgALTweight": "1",
        "cfgResFileName": "\/home\/archita\/alice\/O2Physics\/Tutorials\/PWGEM\/Cocktail\/files\/resolution\/Resolution_PbPb5TeV.root",
        "cfgEffFileName": "\/home\/archita\/alice\/O2Physics\/Tutorials\/PWGEM\/Cocktail\/files\/resolution\/EffMult.root",
        "cfgMinOpAng": "0",
        "cfgDoRapidityCut": "false",
        "cfgRapidityCut": "1",
        "cfgNBinsPhi": "240",
        "cfgMinPhi": "0",
        "cfgMaxPhi": "6.28318548",
        "cfgNBinsRap": "240",
        "cfgMinRap": "-1.20000005",
        "cfgMaxRap": "1.20000005",
        "cfgEffHistName": "fhwEffpT",
        "cfgResPHistName": "ptSlices",
        "cfgResPtHistName": "RelPtResArrCocktail",
        "cfgResEtaHistName": "EtaResArr",
        "cfgResPhiPosHistName": "PhiPosResArr",
        "cfgResPhiNegHistName": "PhiEleResArr",
        "cfgDCAFileName": "\/home\/archita\/alice\/O2Physics\/Tutorials\/PWGEM\/Cocktail\/files\/resolution\/DCA.root",
        "cfgDCAHistName": "fh_DCAtemplate",
        "cfgMultFileName": "\/home\/archita\/alice\/O2Physics\/Tutorials\/PWGEM\/Cocktail\/files\/resolution\/EffMult.root",
        "cfgMultHistPtName": "fhwMultpT",
        "cfgMultHistPt2Name": "fhwMultpT_upperlimit",
        "cfgMultHistMtName": "fhwMultmT",
        "cfgMultHistMt2Name": "fhwMultmT_upperlimit",
        "cfgKWNBins": "10000",
        "cfgKWMax": "1.10000002",
        "cfgDoVirtPh": "false",
        "cfgPhotonPtFileName": "",
        "cfgPhotonPtDirName": "",
        "cfgPhotonPtFuncName": "111_pt",
        "cfgDCATemplateEdges": {
            "values": [
                "0",
                "0.29999999999999999",
                "0.40000000000000002",
                "0.59999999999999998",
                "1",
                "2"
            ]
        }
    },
    "internal-dpl-injected-dummy-sink": "",
    "internal-dpl-aod-global-analysis-file-sink": ""
}
